ap_rest_client/__init__.py
ap_rest_client/ap_protocol.py
ap_rest_client/data/langgraph.json
ap_rest_client/logging_config.py
ap_rest_client/models/__init__.py
ap_rest_client/models/graph_config.py
ap_rest_client/models/graph_state.py
ap_rest_client-0.0.7.dist-info/LICENSE
ap_rest_client-0.0.7.dist-info/METADATA
ap_rest_client-0.0.7.dist-info/WHEEL
ap_rest_client-0.0.7.dist-info/RECORD
