Metadata-Version: 2.3
Name: ap-rest-client
Version: 0.0.7
Summary: 
Author: brisacoder
Author-email: dev@brisa.ai
Requires-Python: >=3.13,<4.0
Classifier: Programming Language :: Python :: 3
Classifier: Programming Language :: Python :: 3.13
Requires-Dist: fastapi[standard] (==0.115.11)
Requires-Dist: langchain (==0.3.20)
Requires-Dist: langchain-openai (==0.3.8)
Requires-Dist: langgraph (==0.3.11)
Requires-Dist: langgraph-cli[inmem] (==0.1.77)
Requires-Dist: langgraph-sdk (==0.1.57)
Requires-Dist: packaging (==24.2)
Requires-Dist: pydantic (==2.10.6)
Requires-Dist: pydantic-settings (==2.8.1)
Requires-Dist: python-dotenv (==1.0.1)
Requires-Dist: python-json-logger (>=3.3.0,<4.0.0)
Requires-Dist: requests (==2.32.3)
